FlexTransform/FlexT.py
FlexTransform/FlexTBatch.py
FlexTransform/FlexTransform.py
FlexTransform/__init__.py
FlexTransform/Configuration/Config.py
FlexTransform/Configuration/__init__.py
FlexTransform/Configuration/ConfigFunctions/ConfigFunctionManager.py
FlexTransform/Configuration/ConfigFunctions/GlobalFunctions.py
FlexTransform/Configuration/ConfigFunctions/__init__.py
FlexTransform/OntologyOracle/OntologyOracle.py
FlexTransform/OntologyOracle/__init__.py
FlexTransform/SchemaParser/SchemaParser.py
FlexTransform/SchemaParser/__init__.py
FlexTransform/SchemaParser/TransformFunctions/CFM13Functions.py
FlexTransform/SchemaParser/TransformFunctions/CFM20Functions.py
FlexTransform/SchemaParser/TransformFunctions/GlobalFunctions.py
FlexTransform/SchemaParser/TransformFunctions/STIXFunctions.py
FlexTransform/SchemaParser/TransformFunctions/TransformFunctionManager.py
FlexTransform/SchemaParser/TransformFunctions/__init__.py
FlexTransform/SyntaxParser/CSVParser.py
FlexTransform/SyntaxParser/DictionaryParser.py
FlexTransform/SyntaxParser/KVParser.py
FlexTransform/SyntaxParser/Parser.py
FlexTransform/SyntaxParser/XMLParser.py
FlexTransform/SyntaxParser/__init__.py
FlexTransform/SyntaxParser/DICTParsers/__init__.py
FlexTransform/SyntaxParser/DICTParsers/iSightReport.py
FlexTransform/SyntaxParser/XMLParsers/CFM13.py
FlexTransform/SyntaxParser/XMLParsers/CFM20Alert.py
FlexTransform/SyntaxParser/XMLParsers/STIX.py
FlexTransform/SyntaxParser/XMLParsers/__init__.py
FlexTransform/resources/cybox.zip
FlexTransform/resources/indicator-tbox.owl
FlexTransform/resources/ramrod.zip
FlexTransform/resources/stix.zip
FlexTransform/resources/test.owl
FlexTransform/resources/transform.owl
FlexTransform/resources/sampleConfigurations/MBL.cfg
FlexTransform/resources/sampleConfigurations/cfm13.cfg
FlexTransform/resources/sampleConfigurations/cfm20alert.cfg
FlexTransform/resources/sampleConfigurations/crisp_json.cfg
FlexTransform-1.2.1.dist-info/DESCRIPTION.rst
FlexTransform-1.2.1.dist-info/METADATA
FlexTransform-1.2.1.dist-info/RECORD
FlexTransform-1.2.1.dist-info/WHEEL
FlexTransform-1.2.1.dist-info/entry_points.txt
FlexTransform-1.2.1.dist-info/metadata.json
FlexTransform-1.2.1.dist-info/top_level.txt
