Metadata-Version: 2.0
Name: FlexTransform
Version: 1.2.1
Summary: Flexible Transform is a tool that enables dynamic translation between formats
Home-page: https://github.com/anl-cyberscience/FlexTransform/
Author: The CFM Team
Author-email: fedhelp@anl.gov
License: UNKNOWN
Platform: UNKNOWN
Classifier: Development Status :: 5 - Production/Stable
Classifier: Intended Audience :: Information Technology
Classifier: Topic :: Security
Classifier: License :: Other/Proprietary License
Classifier: Programming Language :: Python :: 3
Classifier: Programming Language :: Python :: 3.3
Classifier: Programming Language :: Python :: 3.4
Classifier: Programming Language :: Python :: 3.5
Classifier: Programming Language :: Python :: 3.6
Requires-Dist: arrow
Requires-Dist: dumper
Requires-Dist: lxml
Requires-Dist: python-dateutil
Requires-Dist: pytz
Requires-Dist: rdflib
